LICENSE.txt
README.md
setup.py
Malas.egg-info/PKG-INFO
Malas.egg-info/SOURCES.txt
Malas.egg-info/dependency_links.txt
Malas.egg-info/requires.txt
Malas.egg-info/top_level.txt
malas/__init__.py
malas/__main__.py
malas/configuration_type_validator.py
malas/connection_ssh.py
malas/connection_validator.py
malas/device_info_validator.py
malas/file_validator.py
malas/ip_addr_validator.py
malas/program_orchestrator.py
malas/program_supplementals.py