Metadata-Version: 2.1
Name: Malas
Version: 1.0.210930.1
Summary: Malas (Multi-vendor automation leverage at slouching)
Home-page: https://github.com/destrianto/malas
Author: Ade Destrianto
Author-email: ade.destrianto@mail.ru
License: MIT
Download-URL: https://github.com/destrianto/malas/releases/download/1.0.210930.0001/malas_1.0.210930.0001.zip
Keywords: multi-vendor,network,automation
Platform: UNKNOWN
Classifier: Environment :: Console
Classifier: Intended Audience :: System Administrators
Classifier: License :: OSI Approved :: MIT License
Classifier: Natural Language :: English
Classifier: Programming Language :: Python :: 3.9
Classifier: Topic :: System :: Networking
Requires-Python: >=3.9
